audit/__init__.py
audit/admin.py
audit/apps.py
audit/middleware.py
audit/models.py
audit/signals.py
audit/tests.py
audit/utils.py
audit/views.py
audit/migrations/0001_initial.py
audit/migrations/0002_alter_auditlog_content_type_alter_auditlog_object_id.py
audit/migrations/__init__.py
django_audit_library-1.0.3.dist-info/licenses/LICENSE
django_audit_library-1.0.3.dist-info/METADATA
django_audit_library-1.0.3.dist-info/WHEEL
django_audit_library-1.0.3.dist-info/top_level.txt
django_audit_library-1.0.3.dist-info/RECORD
