Metadata-Version: 2.4
Name: django-audit-library
Version: 1.0.3
Summary: A comprehensive Django audit logging library for tracking model changes, user actions, and system events
Home-page: https://github.com/mcwamsie/django_audit-library
Author: Tinashe Makwarimba
Author-email: Tinashe Makwarimba <tinashe@mcwamsie.com>
License: MIT
Project-URL: Homepage, https://github.com/mcwamsie/django_audit_library
Project-URL: Documentation, https://github.com/mcwamsie/django_audit_library#readme
Project-URL: Repository, https://github.com/mcwamsie/django_audit_library.git
Project-URL: Bug Tracker, https://github.com/mcwamsie/django_audit_library/issues
Keywords: django,audit,logging,security,tracking,changes
Classifier: Development Status :: 5 - Production/Stable
Classifier: Environment :: Web Environment
Classifier: Framework :: Django
Classifier: Framework :: Django :: 3.2
Classifier: Framework :: Django :: 4.0
Classifier: Framework :: Django :: 4.1
Classifier: Framework :: Django :: 4.2
Classifier: Intended Audience :: Developers
Classifier: License :: OSI Approved :: MIT License
Classifier: Operating System :: OS Independent
Classifier: Programming Language :: Python
Classifier: Programming Language :: Python :: 3
Classifier: Programming Language :: Python :: 3.8
Classifier: Programming Language :: Python :: 3.9
Classifier: Programming Language :: Python :: 3.10
Classifier: Programming Language :: Python :: 3.11
Classifier: Topic :: Internet :: WWW/HTTP
Classifier: Topic :: Internet :: WWW/HTTP :: Dynamic Content
Classifier: Topic :: Software Development :: Libraries :: Python Modules
Classifier: Topic :: System :: Logging
Classifier: Topic :: System :: Systems Administration :: Authentication/Directory
Requires-Python: >=3.8
License-File: LICENSE
Requires-Dist: Django>=3.2
Dynamic: author
Dynamic: home-page
Dynamic: license-file
Dynamic: requires-python
